qualia/__init__.py
qualia-0.0.1.dist-info/LICENSE
qualia-0.0.1.dist-info/METADATA
qualia-0.0.1.dist-info/WHEEL
qualia-0.0.1.dist-info/top_level.txt
qualia-0.0.1.dist-info/RECORD
