Metadata-Version: 2.1
Name: qualia
Version: 0.0.1
Summary: qualia
Home-page: https://github.com/ursiform/qualia
Author: Afshin T. Darian
Author-email: qualia@darian.af
License: UNKNOWN
Platform: UNKNOWN
Classifier: Programming Language :: Python :: 3
Classifier: Operating System :: OS Independent
